Workbook

Sheet Influence Matrix
B3: {=TRANSPOSE(A4:A45)} -> Addiction | C3: Agriculture | D3: Authoritarianism | E3: Birthrate | F3: Corruption | G3: Cost of Living | H3: Crime | I3: Deathrate | J3: Discrimination | K3: Diversity | L3: Edu: Access | M3: Edu: Cost | N3: Edu: Quality | O3: Employment | P3: Energy Production | Q3: Equality | R3: Family Values | S3: Freedom of Speech | T3: Gun Rights | U3: HC Access | V3: HC Cost | W3: HC Quality | X3: Homelessness | Y3: Immigration | Z3: Infrastructure | AA3: Innovation | AB3: Law Enforcment | AC3: Liberty | AD3: Market Freedom | AE3: Mental Health | AF3: Military Budget | AG3: Minimum Wage | AH3: Pollution | AI3: Poverty | AJ3: Public Trust | AK3: Purpose/Meaning | AL3: Religion | AM3: Sickness/Disease | AN3: Taxes | AO3: Tech | AP3: Transportation | AQ3: Welfare Support
A4: =Sliders!A1 -> Addiction | B4: 1 | C4: 0.09 | D4: 0.08 | E4: 0 | F4: 0 | G4: 0 | H4: 0 | I4: 0 | J4: 0 | K4: 0 | L4: 0 | M4: 0 | N4: 0 | O4: 0 | P4: 0 | Q4: 0 | R4: 0 | S4: 0 | T4: 0 | U4: 0 | V4: 0 | W4: 0 | X4: 0 | Y4: 0 | Z4: 0 | AA4: 0 | AB4: 0 | AC4: 0 | AD4: 0 | AE4: 0 | AF4: 0 | AG4: 0 | AH4: 0 | AI4: 0 | AJ4: 0 | AK4: 0 | AL4: 0 | AM4: 0 | AN4: 0 | AO4: 0 | AP4: 0 | AQ4: 0
A5: =Sliders!A2 -> Agriculture | B5: -0.08 | C5: 1 | D5: -0.15 | E5: 0.05 | F5: 0 | G5: 0 | H5: 0 | I5: 0 | J5: 0 | K5: 0 | L5: 0 | M5: 0 | N5: 0 | O5: 0 | P5: 0 | Q5: 0 | R5: 0 | S5: 0 | T5: 0 | U5: 0 | V5: 0 | W5: 0 | X5: 0 | Y5: 0 | Z5: 0 | AA5: 0 | AB5: 0 | AC5: 0 | AD5: 0 | AE5: 0 | AF5: 0 | AG5: 0 | AH5: 0 | AI5: 0 | AJ5: 0 | AK5: 0 | AL5: 0 | AM5: 0 | AN5: 0 | AO5: 0 | AP5: 0 | AQ5: 0
A6: =Sliders!A3 -> Authoritarianism | B6: 0 | C6: 0.17 | D6: 1 | E6: 0 | F6: 0 | G6: 0 | H6: 0 | I6: 0 | J6: 0 | K6: 0 | L6: 0 | M6: 0 | N6: 0 | O6: 0 | P6: 0 | Q6: 0 | R6: 0 | S6: 0 | T6: 0 | U6: 0 | V6: 0 | W6: 0 | X6: 0 | Y6: 0 | Z6: 0 | AA6: 0 | AB6: 0 | AC6: 0 | AD6: 0 | AE6: 0 | AF6: 0 | AG6: 0 | AH6: 0 | AI6: 0 | AJ6: 0 | AK6: 0 | AL6: 0 | AM6: 0 | AN6: 0 | AO6: 0 | AP6: 0 | AQ6: 0
A7: =Sliders!A4 -> Birthrate | B7: -0.16 | C7: 0.13 | D7: 0 | E7: 1 | F7: 0 | G7: 0 | H7: 0 | I7: 0 | J7: 0 | K7: 0 | L7: 0 | M7: 0 | N7: 0 | O7: 0 | P7: 0 | Q7: 0 | R7: 0 | S7: 0 | T7: 0 | U7: 0 | V7: 0 | W7: 0 | X7: 0 | Y7: 0 | Z7: 0 | AA7: 0 | AB7: 0 | AC7: 0 | AD7: 0 | AE7: 0 | AF7: 0 | AG7: 0 | AH7: 0 | AI7: 0 | AJ7: 0 | AK7: 0 | AL7: 0 | AM7: 0 | AN7: 0 | AO7: 0 | AP7: 0 | AQ7: 0
A8: =Sliders!A5 -> Corruption | B8: 0 | C8: 0 | D8: 0.3 | E8: 0 | F8: 1 | G8: 0 | H8: 0 | I8: 0 | J8: 0 | K8: 0 | L8: 0 | M8: 0 | N8: 0 | O8: 0 | P8: 0 | Q8: 0 | R8: 0 | S8: 0 | T8: 0 | U8: 0 | V8: 0 | W8: 0 | X8: 0 | Y8: 0 | Z8: 0 | AA8: 0 | AB8: 0 | AC8: 0 | AD8: 0 | AE8: 0 | AF8: 0 | AG8: 0 | AH8: 0 | AI8: 0 | AJ8: 0 | AK8: 0 | AL8: 0 | AM8: 0 | AN8: 0 | AO8: 0 | AP8: 0 | AQ8: 0
A9: =Sliders!A6 -> Cost of Living | B9: 0.19 | C9: -0.16 | D9: 0 | E9: 0.04 | F9: 0 | G9: 1 | H9: 0 | I9: 0 | J9: 0 | K9: 0 | L9: 0 | M9: 0 | N9: 0 | O9: 0 | P9: 0 | Q9: 0 | R9: 0 | S9: 0 | T9: 0 | U9: 0 | V9: 0 | W9: 0 | X9: 0 | Y9: 0 | Z9: 0 | AA9: 0 | AB9: 0 | AC9: 0 | AD9: 0 | AE9: 0 | AF9: 0 | AG9: 0 | AH9: 0 | AI9: 0 | AJ9: 0 | AK9: 0 | AL9: 0 | AM9: 0 | AN9: 0 | AO9: 0 | AP9: 0 | AQ9: 0
A10: =Sliders!A7 -> Crime | B10: 0.3 | C10: -0.13 | D10: -0.06 | E10: 0 | F10: 0 | G10: 0 | H10: 1 | I10: 0 | J10: 0 | K10: 0 | L10: 0 | M10: 0 | N10: 0 | O10: 0 | P10: 0 | Q10: 0 | R10: 0 | S10: 0 | T10: 0 | U10: 0 | V10: 0 | W10: 0 | X10: 0 | Y10: 0 | Z10: 0 | AA10: 0 | AB10: 0 | AC10: 0 | AD10: 0 | AE10: 0 | AF10: 0 | AG10: 0 | AH10: 0 | AI10: 0 | AJ10: 0 | AK10: 0 | AL10: 0 | AM10: 0 | AN10: 0 | AO10: 0 | AP10: 0 | AQ10: 0
A11: =Sliders!A8 -> Deathrate | B11: 0.31 | C11: 0.14 | D11: -0.13 | E11: -0.02 | F11: 0 | G11: 0 | H11: 0 | I11: 1 | J11: 0 | K11: 0 | L11: 0 | M11: 0 | N11: 0 | O11: 0 | P11: 0 | Q11: 0 | R11: 0 | S11: 0 | T11: 0 | U11: 0 | V11: 0 | W11: 0 | X11: 0 | Y11: 0 | Z11: 0 | AA11: 0 | AB11: 0 | AC11: 0 | AD11: 0 | AE11: 0 | AF11: 0 | AG11: 0 | AH11: 0 | AI11: 0 | AJ11: 0 | AK11: 0 | AL11: 0 | AM11: 0 | AN11: 0 | AO11: 0 | AP11: 0 | AQ11: 0
A12: =Sliders!A9 -> Discrimination | B12: 0 | C12: 0.12 | D12: 0.27 | E12: 0 | F12: 0 | G12: 0 | H12: 0 | I12: 0 | J12: 1 | K12: 0 | L12: 0 | M12: 0 | N12: 0 | O12: 0 | P12: 0 | Q12: 0 | R12: 0 | S12: 0 | T12: 0 | U12: 0 | V12: 0 | W12: 0 | X12: 0 | Y12: 0 | Z12: 0 | AA12: 0 | AB12: 0 | AC12: 0 | AD12: 0 | AE12: 0 | AF12: 0 | AG12: 0 | AH12: 0 | AI12: 0 | AJ12: 0 | AK12: 0 | AL12: 0 | AM12: 0 | AN12: 0 | AO12: 0 | AP12: 0 | AQ12: 0
A13: =Sliders!A10 -> Diversity | B13: 0 | C13: 0.11 | D13: -0.2 | E13: 0 | F13: 0 | G13: 0 | H13: 0 | I13: 0 | J13: 0 | K13: 1 | L13: 0 | M13: 0 | N13: 0 | O13: 0 | P13: 0 | Q13: 0 | R13: 0 | S13: 0 | T13: 0 | U13: 0 | V13: 0 | W13: 0 | X13: 0 | Y13: 0 | Z13: 0 | AA13: 0 | AB13: 0 | AC13: 0 | AD13: 0 | AE13: 0 | AF13: 0 | AG13: 0 | AH13: 0 | AI13: 0 | AJ13: 0 | AK13: 0 | AL13: 0 | AM13: 0 | AN13: 0 | AO13: 0 | AP13: 0 | AQ13: 0
A14: =Sliders!A11 -> Edu: Access | B14: -0.07 | C14: 0.09 | D14: 0 | E14: -0.07 | F14: 0 | G14: 0 | H14: 0 | I14: 0 | J14: 0 | K14: 0 | L14: 1 | M14: 0 | N14: 0 | O14: 0 | P14: 0 | Q14: 0 | R14: 0 | S14: 0 | T14: 0 | U14: 0 | V14: 0 | W14: 0 | X14: 0 | Y14: 0 | Z14: 0 | AA14: 0 | AB14: 0 | AC14: 0 | AD14: 0 | AE14: 0 | AF14: 0 | AG14: 0 | AH14: 0 | AI14: 0 | AJ14: 0 | AK14: 0 | AL14: 0 | AM14: 0 | AN14: 0 | AO14: 0 | AP14: 0 | AQ14: 0
A15: =Sliders!A12 -> Edu: Cost | B15: 0 | C15: -0.08 | D15: 0 | E15: 0.13 | F15: 0 | G15: 0 | H15: 0 | I15: 0 | J15: 0 | K15: 0 | L15: 0 | M15: 1 | N15: 0 | O15: 0 | P15: 0 | Q15: 0 | R15: 0 | S15: 0 | T15: 0 | U15: 0 | V15: 0 | W15: 0 | X15: 0 | Y15: 0 | Z15: 0 | AA15: 0 | AB15: 0 | AC15: 0 | AD15: 0 | AE15: 0 | AF15: 0 | AG15: 0 | AH15: 0 | AI15: 0 | AJ15: 0 | AK15: 0 | AL15: 0 | AM15: 0 | AN15: 0 | AO15: 0 | AP15: 0 | AQ15: 0
... A45: =Sliders!A42 -> Welfare Support | B45: 0.22 | C45: 0.18 | D45: 0.14 | E45: 0 | F45: 0 | G45: 0 | H45: 0 | I45: 0 | J45: 0 | K45: 0 | L45: 0 | M45: 0 | N45: 0 | O45: 0 | P45: 0 | Q45: 0 | R45: 0 | S45: 0 | T45: 0 | U45: 0 | V45: 0 | W45: 0 | X45: 0 | Y45: 0 | Z45: 0 | AA45: 0 | AB45: 0 | AC45: 0 | AD45: 0 | AE45: 0 | AF45: 0 | AG45: 0 | AH45: 0 | AI45: 0 | AJ45: 0 | AK45: 0 | AL45: 0 | AM45: 0 | AN45: 0 | AO45: 0 | AP45: 0 | AQ45: 1

Sheet Sliders
A1: Addiction
A2: Agriculture
A3: Authoritarianism | F3: Expanded
A4: Birthrate | C4: DO NOT TOUCH: COLUMN A! | F4: Climate Stability | J4: Composites
A5: Corruption | F5: CO2 Emmisions
A6: Cost of Living | F6: Creativity
A7: Crime | F7: LGBTQIA+
A8: Deathrate | F8: Migration
A9: Discrimination | F9: Resilience
A10: Diversity | F10: Sexual Freedom
A11: Edu: Access | F11: Stigma
A12: Edu: Cost | F12: Surveillance
A13: Edu: Quality | F13: Wage Gap
A14: Employment | F14: Sex Ratio
A15: Energy Production | F15: Patriarchy
A16: Equality
A17: Family Values
A18: Freedom of Speech
A19: Gun Rights
A20: HC Access | F20: Healthcare
A21: HC Cost | F21: Healthcare Access
A22: HC Quality | F22: Healthcare Cost
A23: Homelessness | F23: Healthcare Quality
A24: Immigration
A25: Infrastructure
A26: Innovation
A27: Law Enforcment
A28: Liberty
A29: Market Freedom
A30: Mental Health
A31: Military Budget
A32: Minimum Wage
A33: Pollution
A34: Poverty
A35: Public Trust
... A42: Welfare Support

Sheet Indicators
B3: Approved | I3: Ideas
B4: Quality of Living | I4: Capitalism
B5: Social Tension | I5: Nihilism
B6: Societal Cohesion

Sheet Media Headlines

Sheet Math
